{
  "skills": [
    {
      "group": "software",
      "skills": [
        "assembler",
        "C++",
        "python"
      ]
    },
    {
      "group": "hardware",
      "skills": [
        "analogue circuit design",
        "design for EMC",
        "PCB layout"
      ]
    },
    {
      "group": "soft skills",
      "skills": [
        "personal presence",
        "leadership"
      ]
    }
  ],
  "roles": [
    {
      "title": "software engineer",
      "required skills": [
        {
          "dateDefined": "2021-01-06T12:01:01.000Z",
          "skills": [
            {
              "group": "software",
              "skills": [
                {
                  "skill": "assembler",
                  "level": 3
                },
                {
                  "skill": "C++",
                  "level": 3
                },
                {
                  "skill": "python",
                  "level": 3
                }
              ]
            },
            {
              "group": "hardware",
              "skills": [
                {
                  "skill": "analogue circuit design",
                  "level": 1
                },
                {
                  "skill": "design for EMC",
                  "level": 1
                },
                {
                  "skill": "PCB layout",
                  "level": 1
                }
              ]
            },
            {
              "group": "soft skills",
              "skills": [
                {
                  "skill": "personal presence",
                  "level": 1
                },
                {
                  "skill": "leadership",
                  "level": 1
                }
              ]
            }
          ]
        }
      ]
    },
    {
      "title": "hardware engineer",
      "required skills": [
        {
          "dateDefined": "2021-01-06T12:01:01.000Z",
          "skills": [
            {
              "group": "software",
              "skills": [
                {
                  "skill": "driver creation",
                  "level": 1
                },
                {
                  "skill": "unit testing",
                  "level": 1
                }
              ]
            },
            {
              "group": "hardware",
              "skills": [
                {
                  "skill": "analogue circuit design",
                  "level": 3
                },
                {
                  "skill": "digital circuit design",
                  "level": 3
                }
              ]
            }
          ]
        },
        {
          "dateDefined": "2021-01-07T12:01:01.000Z",
          "skills": [
            {
              "group": "software",
              "skills": [
                {
                  "skill": "driver creation",
                  "level": 2
                },
                {
                  "skill": "unit testing",
                  "level": 1
                }
              ]
            },
            {
              "group": "hardware",
              "skills": [
                {
                  "skill": "analogue circuit design",
                  "level": 3
                },
                {
                  "skill": "digital circuit design",
                  "level": 3
                }
              ]
            }
          ]
        },
        {
          "dateDefined": "2021-01-13T12:01:01.000Z",
          "skills": [
            {
              "group": "software",
              "skills": [
                {
                  "skill": "assembler",
                  "level": 1
                },
                {
                  "skill": "C++",
                  "level": 1
                },
                {
                  "skill": "python",
                  "level": 1
                }
              ]
            },
            {
              "group": "hardware",
              "skills": [
                {
                  "skill": "analogue circuit design",
                  "level": 3
                },
                {
                  "skill": "design for EMC",
                  "level": 3
                },
                {
                  "skill": "PCB layout",
                  "level": 2
                }
              ]
            },
            {
              "group": "soft skills",
              "skills": [
                {
                  "skill": "personal presence",
                  "level": 2
                },
                {
                  "skill": "leadership",
                  "level": 2
                }
              ]
            }
          ]
        }
      ]
    },
    {
      "title": "verification engineer",
      "required skills": [
        {
          "dateDefined": "2021-01-06T12:01:01.000Z",
          "skills": [
            {
              "group": "software",
              "skills": [
                {
                  "skill": "driver creation",
                  "level": 1
                },
                {
                  "skill": "unit testing",
                  "level": 1
                }
              ]
            },
            {
              "group": "hardware",
              "skills": [
                {
                  "skill": "analogue circuit design",
                  "level": 3
                },
                {
                  "skill": "digital circuit design",
                  "level": 3
                }
              ]
            }
          ]
        },
        {
          "dateDefined": "2021-01-07T12:01:01.000Z",
          "skills": [
            {
              "group": "software",
              "skills": [
                {
                  "skill": "driver creation",
                  "level": 2
                },
                {
                  "skill": "unit testing",
                  "level": 1
                }
              ]
            },
            {
              "group": "hardware",
              "skills": [
                {
                  "skill": "analogue circuit design",
                  "level": 3
                },
                {
                  "skill": "digital circuit design",
                  "level": 3
                }
              ]
            }
          ]
        },
        {
          "dateDefined": "2021-01-12T12:01:01.000Z",
          "skills": [
            {
              "group": "software",
              "skills": [
                {
                  "skill": "assembler",
                  "level": 3
                },
                {
                  "skill": "C++",
                  "level": 3
                },
                {
                  "skill": "python",
                  "level": 3
                }
              ]
            },
            {
              "group": "hardware",
              "skills": [
                {
                  "skill": "analogue circuit design",
                  "level": 1
                },
                {
                  "skill": "design for EMC",
                  "level": 1
                },
                {
                  "skill": "PCB layout",
                  "level": 1
                }
              ]
            },
            {
              "group": "soft skills",
              "skills": [
                {
                  "skill": "personal presence",
                  "level": 1
                },
                {
                  "skill": "leadership",
                  "level": 1
                }
              ]
            }
          ]
        }
      ]
    }
  ],
  "employees": [
    {
      "name": "Joe Bloggs",
      "email": "joe.bloggs@domain.com",
      "job title": "software engineer",
      "assessments": [
        {
          "assessment timestamp": "2021-01-12T13:05:00.000Z",
          "role": "software engineer",
          "skills": [
            {
              "group": "software",
              "skills": [
                {
                  "skill": "driver creation",
                  "required level": 3,
                  "actual level": 2
                },
                {
                  "skill": "unit testing",
                  "required level": 3,
                  "actual level": 4
                }
              ]
            },
            {
              "group": "hardware",
              "skills": [
                {
                  "skill": "analogue circuit design",
                  "required level": 1,
                  "actual level": 2
                },
                {
                  "skill": "digital circuit design",
                  "required level": 1,
                  "actual level": 2
                }
              ]
            }
          ]
        },
        {
          "assessment timestamp": "2021-01-01T13:05:00.000Z",
          "role": "hardware engineer",
          "skills": [
            {
              "group": "software",
              "skills": [
                {
                  "skill": "driver creation",
                  "required level": 1,
                  "actual level": 2
                },
                {
                  "skill": "unit testing",
                  "required level": 1,
                  "actual level": 3
                }
              ]
            },
            {
              "group": "hardware",
              "skills": [
                {
                  "skill": "analogue circuit design",
                  "required level": 3,
                  "actual level": 4
                },
                {
                  "skill": "digital circuit design",
                  "required level": 3,
                  "actual level": 2
                }
              ]
            }
          ]
        },
        {
          "assessment timestamp": "2021-01-14T00:05:00.340Z",
          "role": "software engineer",
          "skills": [
            {
              "group": "software",
              "skills": [
                {
                  "skill": "assembler",
                  "required level": 3,
                  "actual level": 2
                },
                {
                  "skill": "C++",
                  "required level": 3,
                  "actual level": 4
                },
                {
                  "skill": "python",
                  "required level": 3,
                  "actual level": 4
                }
              ]
            },
            {
              "group": "hardware",
              "skills": [
                {
                  "skill": "analogue circuit design",
                  "required level": 1,
                  "actual level": 2
                },
                {
                  "skill": "design for EMC",
                  "required level": 1,
                  "actual level": 2
                },
                {
                  "skill": "PCB layout",
                  "required level": 1,
                  "actual level": 2
                }
              ]
            },
            {
              "group": "soft skills",
              "skills": [
                {
                  "skill": "personal presence",
                  "required level": 1,
                  "actual level": 2
                },
                {
                  "skill": "leadership",
                  "required level": 1,
                  "actual level": 2
                }
              ]
            }
          ]
        }
      ]
    },
    {
      "name": "An Other",
      "email": "an.other@domain.com",
      "job title": "hardware engineer",
      "assessments": [
        {
          "assessment timestamp": "2021-01-01T13:05:00.000Z",
          "role": "hardware engineer",
          "skills": [
            {
              "group": "software",
              "skills": [
                {
                  "skill": "driver creation",
                  "required level": 3,
                  "actual level": 2
                },
                {
                  "skill": "unit testing",
                  "required level": 3,
                  "actual level": 4
                }
              ]
            },
            {
              "group": "hardware",
              "skills": [
                {
                  "skill": "analogue circuit design",
                  "required level": 1,
                  "actual level": 2
                },
                {
                  "skill": "digital circuit design",
                  "required level": 1,
                  "actual level": 2
                }
              ]
            }
          ]
        },
        {
          "assessment timestamp": "2021-02-05T13:05:00.000Z",
          "role": "hardware engineer",
          "skills": [
            {
              "group": "software",
              "skills": [
                {
                  "skill": "driver creation",
                  "required level": 1,
                  "actual level": 2
                },
                {
                  "skill": "unit testing",
                  "required level": 1,
                  "actual level": 3
                }
              ]
            },
            {
              "group": "hardware",
              "skills": [
                {
                  "skill": "analogue circuit design",
                  "required level": 3,
                  "actual level": 4
                },
                {
                  "skill": "digital circuit design",
                  "required level": 3,
                  "actual level": 2
                }
              ]
            }
          ]
        },
        {
          "assessment timestamp": "2020-12-25T13:05:00.000Z",
          "role": "software engineer",
          "skills": [
            {
              "group": "software",
              "skills": [
                {
                  "skill": "driver creation",
                  "required level": 1,
                  "actual level": 2
                },
                {
                  "skill": "unit testing",
                  "required level": 1,
                  "actual level": 3
                }
              ]
            },
            {
              "group": "hardware",
              "skills": [
                {
                  "skill": "analogue circuit design",
                  "required level": 3,
                  "actual level": 4
                },
                {
                  "skill": "digital circuit design",
                  "required level": 3,
                  "actual level": 2
                }
              ]
            }
          ]
        },
        {
          "assessment timestamp": "2021-03-16T13:05:00.000Z",
          "role": "hardware engineer",
          "skills": [
            {
              "group": "software",
              "skills": [
                {
                  "skill": "assembler",
                  "required level": 1,
                  "actual level": 2
                },
                {
                  "skill": "C++",
                  "required level": 1,
                  "actual level": 3
                },
                {
                  "skill": "python",
                  "required level": 1,
                  "actual level": 2
                }
              ]
            },
            {
              "group": "hardware",
              "skills": [
                {
                  "skill": "analogue circuit design",
                  "required level": 3,
                  "actual level": 3
                },
                {
                  "skill": "design for EMC",
                  "required level": 3,
                  "actual level": 4
                },
                {
                  "skill": "PCB layout",
                  "required level": 2,
                  "actual level": 2
                }
              ]
            },
            {
              "group": "soft skills",
              "skills": [
                {
                  "skill": "personal presence",
                  "required level": 2,
                  "actual level": 2
                },
                {
                  "skill": "leadership",
                  "required level": 2,
                  "actual level": 2
                }
              ]
            }
          ]
        }
      ]
    }
  ],
  "users": [
    {
      "email": "joe.appleton@solent.ac.uk",
      "password": "$2b$10$oo0/iXcUX93xv9bnOVaOTOS5VOyEjIpgdfWWtWfzV4QBrzlm.W5aS"
    }
  ]
}
